serbian_text_converter/__init__.py
serbian_text_converter/converter.py
tests/__init__.py
tests/test_converter.py
serbian_text_converter-0.1.5.dist-info/LICENSE
serbian_text_converter-0.1.5.dist-info/METADATA
serbian_text_converter-0.1.5.dist-info/WHEEL
serbian_text_converter-0.1.5.dist-info/top_level.txt
serbian_text_converter-0.1.5.dist-info/RECORD
